{"jobIds":["39cdb70c-5673-4001-a42e-383771e353e8"],"results":[{"jobId":"39cdb70c-5673-4001-a42e-383771e353e8","result":{"data":{"timestamp":"2026-02-03T00:49:43.107Z","rootActivityId":"7cc652a3-4636-4334-a3bf-31ba168a5a3d","descriptor":{"Select":[{"Kind":1,"Depth":0,"Value":"G0","GroupKeys":[{"Source":{"Entity":"Date Lookup","Property":"month abbr"},"Calc":"G0","IsSameAsSelect":true}],"Name":"Date Lookup.month name"},{"Kind":1,"SecondaryDepth":0,"Value":"G1","GroupKeys":[{"Source":{"Entity":"Date Lookup","Property":"year"},"Calc":"G1","IsSameAsSelect":true}],"Name":"Date Lookup.year"},{"Kind":2,"Value":"M0","Format":"0%;-0%;0%","Name":"Sum(OTP_Monthly_Route_Avg.OTP_Pct)"},{"Kind":2,"Value":"M1","Name":"Measure Table.goal bus or rail"}],"Expressions":{"Primary":{"Groupings":[{"Keys":[{"Source":{"Entity":"Date Lookup","Property":"month abbr"},"Select":0}],"Member":"DM0"}]},"Secondary":{"Groupings":[{"Keys":[{"Source":{"Entity":"Date Lookup","Property":"year"},"Select":1}],"Member":"DM1"}]}},"Limits":{"Secondary":{"Id":"L0","Top":{"Count":60}}},"Version":2},"metrics":{"Version":"1.0.0","Events":[{"Id":"4dad0c1a-a863-46e6-8ef1-26883d22b1fa","Name":"Execute Semantic Query","Component":"DSE","Start":"2026-02-03T00:49:43.1079318Z","End":"2026-02-03T00:49:43.1391896Z"},{"Id":"7776fc34-3d89-4511-930f-b6e958a6161a","ParentId":"4dad0c1a-a863-46e6-8ef1-26883d22b1fa","Name":"Execute DAX Query","Component":"DSE","Start":"2026-02-03T00:49:43.1079318Z","End":"2026-02-03T00:49:43.1391896Z","Metrics":{"RowCount":52}},{"Id":"65A36549-F427-4423-804C-95A7555D12DB","ParentId":"7776fc34-3d89-4511-930f-b6e958a6161a","Name":"Execute Query","Component":"AS","Start":"2026-02-03T00:49:43.13Z","End":"2026-02-03T00:49:43.137Z"},{"Id":"E4F70268-19DA-4FB1-9276-7FA20B85F2F2","ParentId":"65A36549-F427-4423-804C-95A7555D12DB","Name":"Serialize Rowset","Component":"AS","Start":"2026-02-03T00:49:43.137Z","End":"2026-02-03T00:49:43.137Z"}]},"fromCache":false,"dsr":{"Version":2,"MinorVersion":1,"DS":[{"N":"DS0","S":[{"N":"M1","T":3}],"M1":0.73,"SH":[{"DM1":[{"S":[{"N":"G1","T":1}],"G1":"2019"},{"G1":"2023"},{"G1":"2024"},{"G1":"2025"}]}],"PH":[{"DM0":[{"S":[{"N":"G0","T":1,"DN":"D0"}],"G0":0,"X":[{"S":[{"N":"M0","T":3}],"M0":0.7035},{"M0":0.7017},{"M0":0.8244},{"M0":0.8098}]},{"G0":1,"X":[{"M0":0.6475},{"M0":0.7177},{"M0":0.822},{"M0":0.8296}]},{"G0":2,"X":[{"M0":0.7244},{"M0":0.6918},{"M0":0.8042},{"M0":0.7404}]},{"G0":3,"X":[{"M0":0.6266},{"M0":0.6477},{"M0":0.7423},{"M0":0.7485}]},{"G0":4,"X":[{"M0":0.5742},{"M0":0.6472},{"M0":0.7713},{"M0":0.7194}]},{"G0":5,"X":[{"M0":0.6475},{"M0":0.6102},{"M0":0.7715},{"M0":0.7384}]},{"G0":6,"X":[{"M0":0.6828},{"M0":0.6018},{"M0":0.7601},{"M0":0.7399}]},{"G0":7,"X":[{"M0":0.6673},{"M0":0.5888},{"M0":0.7626},{"M0":0.7181}]},{"G0":8,"X":[{"M0":0.6189},{"M0":0.7226},{"M0":0.7399},{"M0":0.782}]},{"G0":9,"X":[{"M0":0.6366},{"M0":0.7577},{"M0":0.7734},{"M0":0.7761}]},{"G0":10,"X":[{"M0":0.6662},{"M0":0.7491},{"M0":0.7857},{"M0":0.7802}]},{"G0":11,"X":[{"M0":0.6735},{"M0":0.8215},{"M0":0.8221}]}]}],"IC":true,"HAD":true,"ValueDicts":{"D0":["Jan","Feb","Mar","Apr","May","Jun","Jul","Aug","Sep","Oct","Nov","Dec"]}}]}}}}]}