{"jobIds":["c03c92fb-abc3-4187-a796-0cfcd7738a33"],"results":[{"jobId":"c03c92fb-abc3-4187-a796-0cfcd7738a33","result":{"data":{"timestamp":"2026-02-06T19:55:09.268Z","rootActivityId":"86bf2183-8ee9-426f-a832-3ff048e87642","descriptor":{"Select":[{"Kind":1,"Depth":0,"Value":"G0","GroupKeys":[{"Source":{"Entity":"Date Lookup","Property":"month abbr"},"Calc":"G0","IsSameAsSelect":true}],"Name":"Date Lookup.month name"},{"Kind":1,"SecondaryDepth":0,"Value":"G1","GroupKeys":[{"Source":{"Entity":"Date Lookup","Property":"year"},"Calc":"G1","IsSameAsSelect":true}],"Name":"Date Lookup.year"},{"Kind":2,"Value":"M0","Format":"0%;-0%;0%","Name":"Sum(OTP_Monthly_Route_Avg.OTP_Pct)"},{"Kind":2,"Value":"M1","Name":"Measure Table.goal bus or rail"}],"Expressions":{"Primary":{"Groupings":[{"Keys":[{"Source":{"Entity":"Date Lookup","Property":"month abbr"},"Select":0}],"Member":"DM0"}]},"Secondary":{"Groupings":[{"Keys":[{"Source":{"Entity":"Date Lookup","Property":"year"},"Select":1}],"Member":"DM1"}]}},"Limits":{"Secondary":{"Id":"L0","Top":{"Count":60}}},"Version":2},"metrics":{"Version":"1.0.0","Events":[{"Id":"d5fa1eae-f900-4cab-9827-07e870bdc19e","Name":"Execute Semantic Query","Component":"DSE","Start":"2026-02-06T19:55:09.2686879Z","End":"2026-02-06T19:55:09.2999408Z"},{"Id":"e9591050-4d4f-445b-9d56-532eb04d633d","ParentId":"d5fa1eae-f900-4cab-9827-07e870bdc19e","Name":"Execute DAX Query","Component":"DSE","Start":"2026-02-06T19:55:09.2686879Z","End":"2026-02-06T19:55:09.2843125Z","Metrics":{"RowCount":16}},{"Id":"78F3D986-CFD2-4148-9814-7CF5A1E1C5F4","ParentId":"e9591050-4d4f-445b-9d56-532eb04d633d","Name":"Execute Query","Component":"AS","Start":"2026-02-06T19:55:09.29Z","End":"2026-02-06T19:55:09.293Z"},{"Id":"574AE2ED-8F2B-4FED-BE43-E9DAF1F4BFF0","ParentId":"78F3D986-CFD2-4148-9814-7CF5A1E1C5F4","Name":"Serialize Rowset","Component":"AS","Start":"2026-02-06T19:55:09.293Z","End":"2026-02-06T19:55:09.293Z"}]},"fromCache":false,"dsr":{"Version":2,"MinorVersion":1,"DS":[{"N":"DS0","S":[{"N":"M1","T":3}],"M1":0.8,"SH":[{"DM1":[{"S":[{"N":"G1","T":1}],"G1":"2024"},{"G1":"2025"}]}],"PH":[{"DM0":[{"S":[{"N":"G0","T":1,"DN":"D0"}],"G0":0,"X":[{"S":[{"N":"M0","T":3}]},{"I":1,"M0":0.2097}]},{"G0":1,"X":[{"I":1,"M0":0.8418}]},{"G0":2,"X":[{"I":1,"M0":0.8757}]},{"G0":3,"X":[{"I":1,"M0":0.8874}]},{"G0":4,"X":[{"I":1,"M0":0.8693}]},{"G0":5,"X":[{"I":1,"M0":0.8967}]},{"G0":6,"X":[{"I":1,"M0":0.894}]},{"G0":7,"X":[{"I":1,"M0":0.8947}]},{"G0":8,"X":[{"I":1,"M0":0.9008}]},{"G0":9,"X":[{"M0":0.8885},{"M0":0.8619}]},{"G0":10,"X":[{"M0":0.8838}]},{"G0":11,"X":[{"M0":0.8834}]}]}],"IC":true,"HAD":true,"ValueDicts":{"D0":["Jan","Feb","Mar","Apr","May","Jun","Jul","Aug","Sep","Oct","Nov","Dec"]}}]}}}}]}