{"jobIds":["d274c9f3-ad08-4497-9d2c-2bd0bd13fb39"],"results":[{"jobId":"d274c9f3-ad08-4497-9d2c-2bd0bd13fb39","result":{"data":{"timestamp":"2026-02-11T04:04:29.516Z","rootActivityId":"92a864f2-2204-4b65-8965-3f1cb45ad32b","descriptor":{"Select":[{"Kind":2,"Value":"M0","Format":"#,0","Name":"Sum(Ridership_Monthly_Route_Avg.Avg_Riders)"},{"Kind":1,"Depth":0,"Value":"G0","GroupKeys":[{"Source":{"Entity":"Date Lookup","Property":"month abbr"},"Calc":"G0","IsSameAsSelect":true}],"Name":"Date Lookup.month name"},{"Kind":1,"SecondaryDepth":0,"Value":"G1","GroupKeys":[{"Source":{"Entity":"Date Lookup","Property":"year"},"Calc":"G1","IsSameAsSelect":true}],"Name":"Date Lookup.year"}],"Expressions":{"Primary":{"Groupings":[{"Keys":[{"Source":{"Entity":"Date Lookup","Property":"month abbr"},"Select":1}],"Member":"DM0"}]},"Secondary":{"Groupings":[{"Keys":[{"Source":{"Entity":"Date Lookup","Property":"year"},"Select":2}],"Member":"DM1"}]}},"Limits":{"Secondary":{"Id":"L0","Top":{"Count":60}}},"Version":2},"metrics":{"Version":"1.0.0","Events":[{"Id":"22a4e048-cf4d-4c99-ab76-372767272870","Name":"Execute Semantic Query","Component":"DSE","Start":"2026-02-11T04:04:29.5168082Z","End":"2026-02-11T04:04:29.5324364Z"},{"Id":"b8a48042-8a78-4b10-a034-aa91ee6d3ba4","ParentId":"22a4e048-cf4d-4c99-ab76-372767272870","Name":"Execute DAX Query","Component":"DSE","Start":"2026-02-11T04:04:29.5168082Z","End":"2026-02-11T04:04:29.5324364Z","Metrics":{"RowCount":0}},{"Id":"F50194DA-8534-4962-926B-D90581F6ECF3","ParentId":"b8a48042-8a78-4b10-a034-aa91ee6d3ba4","Name":"Execute Query","Component":"AS","Start":"2026-02-11T04:04:29.537Z","End":"2026-02-11T04:04:29.54Z"},{"Id":"5C72AD00-78AD-4F81-9281-A72FF4C10989","ParentId":"F50194DA-8534-4962-926B-D90581F6ECF3","Name":"Serialize Rowset","Component":"AS","Start":"2026-02-11T04:04:29.54Z","End":"2026-02-11T04:04:29.54Z"}]},"fromCache":false,"dsr":{"Version":2,"MinorVersion":1,"DS":[{"N":"DS0","SH":[{"DM1":[]}],"PH":[{"DM0":[]}],"IC":true,"HAD":true}]}}}}]}