{"jobIds":["7a52d6b3-6d61-497e-94d8-3b57b53c77a5"],"results":[{"jobId":"7a52d6b3-6d61-497e-94d8-3b57b53c77a5","result":{"data":{"timestamp":"2026-02-11T04:04:39.376Z","rootActivityId":"6fa85b5f-0a4c-4ceb-be1e-2e5d75291f65","descriptor":{"Select":[{"Kind":2,"Value":"M0","Format":"#,0","Name":"Sum(Ridership_Monthly_Route_Avg.Avg_Riders)"},{"Kind":1,"Depth":0,"Value":"G0","GroupKeys":[{"Source":{"Entity":"Date Lookup","Property":"month abbr"},"Calc":"G0","IsSameAsSelect":true}],"Name":"Date Lookup.month name"},{"Kind":1,"SecondaryDepth":0,"Value":"G1","GroupKeys":[{"Source":{"Entity":"Date Lookup","Property":"year"},"Calc":"G1","IsSameAsSelect":true}],"Name":"Date Lookup.year"}],"Expressions":{"Primary":{"Groupings":[{"Keys":[{"Source":{"Entity":"Date Lookup","Property":"month abbr"},"Select":1}],"Member":"DM0"}]},"Secondary":{"Groupings":[{"Keys":[{"Source":{"Entity":"Date Lookup","Property":"year"},"Select":2}],"Member":"DM1"}]}},"Limits":{"Secondary":{"Id":"L0","Top":{"Count":60}}},"Version":2},"metrics":{"Version":"1.0.0","Events":[{"Id":"eefb0b05-719b-47c9-8d4c-e4141849eed5","Name":"Execute Semantic Query","Component":"DSE","Start":"2026-02-11T04:04:39.3761105Z","End":"2026-02-11T04:04:39.4073585Z"},{"Id":"b2ae1ece-0df5-435c-8c64-2b98c73aa7dc","ParentId":"eefb0b05-719b-47c9-8d4c-e4141849eed5","Name":"Execute DAX Query","Component":"DSE","Start":"2026-02-11T04:04:39.3761105Z","End":"2026-02-11T04:04:39.4073585Z","Metrics":{"RowCount":0}},{"Id":"D6B4CAB8-6055-4F0E-B92D-8FFFF02038CD","ParentId":"b2ae1ece-0df5-435c-8c64-2b98c73aa7dc","Name":"Execute Query","Component":"AS","Start":"2026-02-11T04:04:39.407Z","End":"2026-02-11T04:04:39.41Z"},{"Id":"4E8ADF87-5D34-4CE2-A4DD-FC595C0DE0D1","ParentId":"D6B4CAB8-6055-4F0E-B92D-8FFFF02038CD","Name":"Serialize Rowset","Component":"AS","Start":"2026-02-11T04:04:39.407Z","End":"2026-02-11T04:04:39.41Z"}]},"fromCache":false,"dsr":{"Version":2,"MinorVersion":1,"DS":[{"N":"DS0","SH":[{"DM1":[]}],"PH":[{"DM0":[]}],"IC":true,"HAD":true}]}}}}]}