{"jobIds":["66edfd9d-a065-4853-a378-dd62ae386e54"],"results":[{"jobId":"66edfd9d-a065-4853-a378-dd62ae386e54","result":{"data":{"timestamp":"2026-02-16T23:31:54.86Z","rootActivityId":"cf8ce56c-4a4a-4048-9128-0f4fb5344525","descriptor":{"Select":[{"Kind":1,"Depth":0,"Value":"G0","GroupKeys":[{"Source":{"Entity":"Date Lookup","Property":"month abbr"},"Calc":"G0","IsSameAsSelect":true}],"Name":"Date Lookup.month name"},{"Kind":1,"SecondaryDepth":0,"Value":"G1","GroupKeys":[{"Source":{"Entity":"Date Lookup","Property":"year"},"Calc":"G1","IsSameAsSelect":true}],"Name":"Date Lookup.year"},{"Kind":2,"Value":"M0","Format":"0%;-0%;0%","Name":"Sum(OTP_Monthly_Route_Avg.OTP_Pct)"},{"Kind":2,"Value":"M1","Name":"Measure Table.goal bus or rail"}],"Expressions":{"Primary":{"Groupings":[{"Keys":[{"Source":{"Entity":"Date Lookup","Property":"month abbr"},"Select":0}],"Member":"DM0"}]},"Secondary":{"Groupings":[{"Keys":[{"Source":{"Entity":"Date Lookup","Property":"year"},"Select":1}],"Member":"DM1"}]}},"Limits":{"Secondary":{"Id":"L0","Top":{"Count":60}}},"Version":2},"metrics":{"Version":"1.0.0","Events":[{"Id":"5a0165bf-3a52-4a39-a0ac-0b57ebef36a6","Name":"Execute Semantic Query","Component":"DSE","Start":"2026-02-16T23:31:54.8601688Z","End":"2026-02-16T23:31:54.8914034Z"},{"Id":"e26210e4-384e-4929-b566-c15c1630a4b9","ParentId":"5a0165bf-3a52-4a39-a0ac-0b57ebef36a6","Name":"Execute DAX Query","Component":"DSE","Start":"2026-02-16T23:31:54.8601688Z","End":"2026-02-16T23:31:54.8914034Z","Metrics":{"RowCount":115}},{"Id":"3A138ED8-BD19-46BC-BFA7-7014A42A5A61","ParentId":"e26210e4-384e-4929-b566-c15c1630a4b9","Name":"Execute Query","Component":"AS","Start":"2026-02-16T23:31:54.887Z","End":"2026-02-16T23:31:54.893Z"},{"Id":"ED24E219-4639-48FB-9A31-C9F444EF34E2","ParentId":"3A138ED8-BD19-46BC-BFA7-7014A42A5A61","Name":"Serialize Rowset","Component":"AS","Start":"2026-02-16T23:31:54.893Z","End":"2026-02-16T23:31:54.893Z"}]},"fromCache":false,"dsr":{"Version":2,"MinorVersion":1,"DS":[{"N":"DS0","S":[{"N":"M1","T":3}],"M1":0.73,"SH":[{"DM1":[{"S":[{"N":"G1","T":1}],"G1":"2017"},{"G1":"2018"},{"G1":"2019"},{"G1":"2020"},{"G1":"2021"},{"G1":"2022"},{"G1":"2023"},{"G1":"2024"},{"G1":"2025"}]}],"PH":[{"DM0":[{"S":[{"N":"G0","T":1,"DN":"D0"}],"G0":0,"X":[{"S":[{"N":"M0","T":3}],"M0":0.7562},{"M0":0.7861},{"M0":0.7856},{"M0":0.8087},{"M0":0.8309},{"M0":0.7852},{"M0":0.8148},{"M0":0.8459},{"M0":0.8215}]},{"G0":1,"X":[{"M0":0.7683},{"M0":0.806},{"M0":0.7388},{"M0":0.8181},{"M0":0.8315},{"M0":0.7684},{"M0":0.7651},{"M0":0.8301},{"M0":0.8316}]},{"G0":2,"X":[{"M0":0.7283},{"M0":0.6923},{"M0":0.6076},{"M0":0.8446},{"M0":0.8359},{"M0":0.7765},{"M0":0.654},{"M0":0.8136},{"M0":0.7697}]},{"G0":3,"X":[{"M0":0.6478},{"M0":0.6428},{"M0":0.5882},{"M0":0.8183},{"M0":0.7921},{"M0":0.6743},{"M0":0.686},{"M0":0.7123},{"M0":0.7037}]},{"G0":4,"X":[{"M0":0.5593},{"M0":0.6117},{"M0":0.633},{"M0":0.7997},{"M0":0.8456},{"M0":0.7661},{"M0":0.6827},{"M0":0.86},{"M0":0.7137}]},{"G0":5,"X":[{"M0":0.6091},{"M0":0.6586},{"M0":0.6537},{"I":4,"M0":0.8272},{"M0":0.665},{"M0":0.61},{"M0":0.7622},{"M0":0.8275}]},{"G0":6,"X":[{"M0":0.708},{"M0":0.786},{"M0":0.76},{"I":4,"M0":0.7781},{"M0":0.755},{"M0":0.6374},{"M0":0.7405},{"M0":0.7434}]},{"G0":7,"X":[{"M0":0.6288},{"M0":0.6881},{"M0":0.7776},{"M0":0.7176},{"M0":0.7605},{"M0":0.679},{"M0":0.6538},{"M0":0.6919},{"M0":0.7233}]},{"G0":8,"X":[{"M0":0.6388},{"M0":0.6619},{"M0":0.5829},{"M0":0.6915},{"M0":0.7073},{"I":6,"M0":0.779},{"M0":0.5453},{"M0":0.7366}]},{"G0":9,"X":[{"M0":0.6477},{"M0":0.6936},{"M0":0.7135},{"M0":0.7762},{"M0":0.6947},{"M0":0.7679},{"M0":0.6547},{"M0":0.6306},{"M0":0.6667}]},{"G0":10,"X":[{"M0":0.7226},{"M0":0.7843},{"M0":0.7372},{"M0":0.8},{"M0":0.7147},{"M0":0.657},{"M0":0.6426},{"M0":0.684},{"M0":0.6325}]},{"G0":11,"X":[{"M0":0.7095},{"M0":0.7838},{"M0":0.7847},{"M0":0.8674},{"M0":0.7094},{"M0":0.7917},{"M0":0.6978},{"M0":0.7462},{"M0":0.7029}]}]}],"IC":true,"HAD":true,"ValueDicts":{"D0":["Jan","Feb","Mar","Apr","May","Jun","Jul","Aug","Sep","Oct","Nov","Dec"]}}]}}}}]}